{
  "project_info": {
    "project_number": "969070563286",
    "project_id": "seminarmobile-1cb5e",
    "storage_bucket": "seminarmobile-1cb5e.firebasestorage.app"
  },
  "client": [
    {
      "client_info": {
        "mobilesdk_app_id": "1:969070563286:android:e5cc7436455ea1b6815e77",
        "android_client_info": {
          "package_name": "com.example.socialnetwork"
        }
      },
      "oauth_client": [],
      "api_key": [
        {
          "current_key": "AIzaSyCyJipVz0dvaX_gNG5XbYMcR6EmE5UHe0w"
        }
      ],
      "services": {
        "appinvite_service": {
          "other_platform_oauth_client": []
        }
      }
    }
  ],
  "configuration_version": "1"
}