{
  "project_info": {
    "project_number": "760187401019",
    "project_id": "androi-2-410ab",
    "storage_bucket": "androi-2-410ab.firebasestorage.app"
  },
  "client": [
    {
      "client_info": {
        "mobilesdk_app_id": "1:760187401019:android:b35add574c95d8caa93d1e",
        "android_client_info": {
          "package_name": "social123.oshi"
        }
      },
      "oauth_client": [],
      "api_key": [
        {
          "current_key": "AIzaSyAB-7fPY_WcER19SQKygF5tMANGF6g36us"
        }
      ],
      "services": {
        "appinvite_service": {
          "other_platform_oauth_client": []
        }
      }
    }
  ],
  "configuration_version": "1"
}